spatialtis/__init__.py
spatialtis/_version.py
spatialtis/abc.py
spatialtis/config.py
spatialtis/data_info.py
spatialtis/basic/__init__.py
spatialtis/basic/basic.py
spatialtis/plotting/__init__.py
spatialtis/plotting/basic.py
spatialtis/plotting/interaction.py
spatialtis/plotting/map.py
spatialtis/plotting/regular_spatial.py
spatialtis/plotting/utils.py
spatialtis/preprocessing/__init__.py
spatialtis/preprocessing/read_10x.py
spatialtis/preprocessing/read_images.py
spatialtis/spatial/__init__.py
spatialtis/spatial/autocorr.py
spatialtis/spatial/co_expression.py
spatialtis/spatial/distribution.py
spatialtis/spatial/enrichment.py
spatialtis/spatial/heterogeneity.py
spatialtis/spatial/hotspot.py
spatialtis/spatial/interaction.py
spatialtis/spatial/ncd_markers.py
spatialtis/spatial/neighbors.py
spatialtis/spatial/network.py
spatialtis/spatial/nmd_markers.py
spatialtis/spatial/sv_gene.py
spatialtis/spatial/gcng/__init__.py
spatialtis/spatial/gcng/preprocess.py
spatialtis/spatial/gcng/trainer.py
spatialtis/utils/__init__.py
spatialtis/utils/docs.py
spatialtis/utils/guard.py
spatialtis/utils/io.py
spatialtis/utils/iters.py
spatialtis/utils/log.py
spatialtis-0.5.0.dist-info/LICENSE
spatialtis-0.5.0.dist-info/METADATA
spatialtis-0.5.0.dist-info/WHEEL
spatialtis-0.5.0.dist-info/top_level.txt
spatialtis-0.5.0.dist-info/RECORD
