Metadata-Version: 2.1
Name: spatialtis
Version: 0.5.0
Summary: Ultra-fast spatial analysis toolkit for large-scale spatial single-cell data
Home-page: https://github.com/Mr-Milk/SpatialTis
Author-email: yb97643@um.edu.mo
License: Apache License 2.0
Platform: UNKNOWN
Classifier: License :: OSI Approved :: Apache Software License
Classifier: Programming Language :: Rust
Classifier: Programming Language :: Python :: 3
Classifier: Programming Language :: Python :: 3.8
Classifier: Programming Language :: Python :: 3.9
Classifier: Programming Language :: Python :: 3.10
Classifier: Intended Audience :: Science/Research
Classifier: Topic :: Scientific/Engineering :: Bio-Informatics
Requires-Python: >=3.8
License-File: LICENSE
Requires-Dist: anndata
Requires-Dist: numpy
Requires-Dist: pandas
Requires-Dist: scipy
Requires-Dist: rich[jupyter]
Requires-Dist: spatialtis-core
Requires-Dist: milkviz
Requires-Dist: legendkit
Requires-Dist: thefuzz
Requires-Dist: python-Levenshtein
Provides-Extra: all
Requires-Dist: python-igraph ; extra == 'all'
Requires-Dist: leidenalg ; extra == 'all'
Requires-Dist: scikit-image ; extra == 'all'
Requires-Dist: lightbgm ; extra == 'all'
